Metadata-Version: 2.1
Name: setsapi
Version: 0.1.0
Summary: This is a SETs API for Random Number Generation
Author: Blesson Deep
